DESCRIPTION
MANIFEST.in
README.md
setup.py
scripts/viewie
src/debuggie/__init__.py
src/debuggie/api.py
src/debuggie/urls.py
src/debuggie/views.py
src/debuggie.egg-info/SOURCES.txt
src/debuggie.egg-info/dependency_links.txt
src/debuggie.egg-info/top_level.txt
src/debuggie/templates/debug_status.html
src/debuggie/templates/unauthenticated.html
src/m3_debuggie.egg-info/PKG-INFO
src/m3_debuggie.egg-info/SOURCES.txt
src/m3_debuggie.egg-info/dependency_links.txt
src/m3_debuggie.egg-info/top_level.txt