Metadata-Version: 1.1
Name: m3-debuggie
Version: 2.0.8
Summary: Инструментарий для сбора отладочной информации о Django-системе
